faasit_runtime/__init__.py
faasit_runtime/api.py
faasit_runtime/serverless_function.py
faasit_runtime/worker.py
faasit_runtime/_private/__init__.py
faasit_runtime/durable/__init__.py
faasit_runtime/durable/context.py
faasit_runtime/durable/metadata.py
faasit_runtime/durable/result.py
faasit_runtime/durable/runtime.py
faasit_runtime/durable/state.py
faasit_runtime/durable/models/__init__.py
faasit_runtime/durable/models/local.py
faasit_runtime/durable/models/localonce.py
faasit_runtime/durable/models/pku.py
faasit_runtime/operators/__init__.py
faasit_runtime/runtime/__init__.py
faasit_runtime/runtime/aliyun_runtime.py
faasit_runtime/runtime/faasit_runtime.py
faasit_runtime/runtime/k8s_runtime.py
faasit_runtime/runtime/kn_runtime.py
faasit_runtime/runtime/local_once_runtime.py
faasit_runtime/runtime/local_runtime.py
faasit_runtime/runtime/pku_runtime.py
faasit_runtime/storage/__init__.py
faasit_runtime/storage/redis_db.py
faasit_runtime/storage/rocketmq.py
faasit_runtime/txn/__init__.py
faasit_runtime/txn/saga.py
faasit_runtime/txn/tcc.py
faasit_runtime/utils/__init__.py
faasit_runtime/utils/config.py
faasit_runtime/utils/logging.py
faasit_runtime/workflow/__init__.py
faasit_runtime/workflow/context.py
faasit_runtime/workflow/dag.py
faasit_runtime/workflow/executor.py
faasit_runtime/workflow/ld.py
faasit_runtime/workflow/route.py
faasit_runtime/workflow/workflow.py
faasit_runtime-1.0.0.dist-info/LICENSE
faasit_runtime-1.0.0.dist-info/METADATA
faasit_runtime-1.0.0.dist-info/WHEEL
faasit_runtime-1.0.0.dist-info/top_level.txt
faasit_runtime-1.0.0.dist-info/RECORD
